tests/conftest.py
tests/test_keys_verify.py
tests/test_security.py
tinygenkey/__init__.py
tinygenkey/__init__.pyi
tinygenkey/main.py
tinygenkey/py.typed
tinygenkey-0.3.1.1.dist-info/licenses/LICENSE
tinygenkey-0.3.1.1.dist-info/METADATA
tinygenkey-0.3.1.1.dist-info/WHEEL
tinygenkey-0.3.1.1.dist-info/entry_points.txt
tinygenkey-0.3.1.1.dist-info/top_level.txt
tinygenkey-0.3.1.1.dist-info/RECORD
