Metadata-Version: 2.4
Name: tinygenkey
Version: 0.3.1.1
Summary: A tiny, secure key generator.
Author-email: Razka Rizaldi <razka.rizaldis@gmail.com>
License: MIT
Keywords: key,generator,security,token
Classifier: Programming Language :: Python :: 3
Classifier: License :: OSI Approved :: MIT License
Classifier: Operating System :: OS Independent
Requires-Python: >=3.10
License-File: LICENSE
Dynamic: license-file
